certbot/__init__.py
certbot/achallenges.py
certbot/configuration.py
certbot/crypto_util.py
certbot/errors.py
certbot/interfaces.py
certbot/main.py
certbot/ocsp.py
certbot/py.typed
certbot/reverter.py
certbot/ssl-dhparams.pem
certbot/util.py
certbot/_internal/__init__.py
certbot/_internal/account.py
certbot/_internal/auth_handler.py
certbot/_internal/cert_manager.py
certbot/_internal/client.py
certbot/_internal/constants.py
certbot/_internal/eff.py
certbot/_internal/error_handler.py
certbot/_internal/hooks.py
certbot/_internal/lock.py
certbot/_internal/log.py
certbot/_internal/main.py
certbot/_internal/renewal.py
certbot/_internal/snap_config.py
certbot/_internal/storage.py
certbot/_internal/updater.py
certbot/_internal/cli/__init__.py
certbot/_internal/cli/cli_constants.py
certbot/_internal/cli/cli_utils.py
certbot/_internal/cli/group_adder.py
certbot/_internal/cli/helpful.py
certbot/_internal/cli/paths_parser.py
certbot/_internal/cli/plugins_parsing.py
certbot/_internal/cli/subparsers.py
certbot/_internal/cli/verb_help.py
certbot/_internal/display/__init__.py
certbot/_internal/display/completer.py
certbot/_internal/display/dummy_readline.py
certbot/_internal/display/obj.py
certbot/_internal/display/util.py
certbot/_internal/plugins/__init__.py
certbot/_internal/plugins/disco.py
certbot/_internal/plugins/manual.py
certbot/_internal/plugins/null.py
certbot/_internal/plugins/selection.py
certbot/_internal/plugins/standalone.py
certbot/_internal/plugins/webroot.py
certbot/_internal/tests/__init__.py
certbot/_internal/tests/account_test.py
certbot/_internal/tests/auth_handler_test.py
certbot/_internal/tests/cert_manager_test.py
certbot/_internal/tests/cli_test.py
certbot/_internal/tests/client_test.py
certbot/_internal/tests/configuration_test.py
certbot/_internal/tests/conftest.py
certbot/_internal/tests/crypto_util_test.py
certbot/_internal/tests/eff_test.py
certbot/_internal/tests/error_handler_test.py
certbot/_internal/tests/errors_test.py
certbot-5.0.0.dist-info/licenses/LICENSE.txt
certbot-5.0.0.dist-info/METADATA
certbot-5.0.0.dist-info/WHEEL
certbot-5.0.0.dist-info/entry_points.txt
certbot-5.0.0.dist-info/top_level.txt
certbot-5.0.0.dist-info/RECORD
