Metadata-Version: 2.4
Name: certbot
Version: 5.0.0
Summary: ACME client
Author-email: Certbot Project <certbot-dev@eff.org>
License-Expression: Apache-2.0
Project-URL: Homepage, https://github.com/certbot/certbot
Classifier: Development Status :: 5 - Production/Stable
Classifier: Environment :: Console
Classifier: Intended Audience :: System Administrators
Classifier: Operating System :: POSIX :: Linux
Classifier: Programming Language :: Python
Classifier: Programming Language :: Python :: 3
Classifier: Programming Language :: Python :: 3.10
Classifier: Programming Language :: Python :: 3.11
Classifier: Programming Language :: Python :: 3.12
Classifier: Programming Language :: Python :: 3.13
Classifier: Topic :: Internet :: WWW/HTTP
Classifier: Topic :: Security
Classifier: Topic :: System :: Installation/Setup
Classifier: Topic :: System :: Networking
Classifier: Topic :: System :: Systems Administration
Classifier: Topic :: Utilities
Requires-Python: >=3.10
License-File: LICENSE.txt
Requires-Dist: acme>=5.0.0
Requires-Dist: ConfigArgParse>=1.5.3
Requires-Dist: configobj>=5.0.6
Requires-Dist: cryptography>=43.0.0
Requires-Dist: distro>=1.0.1
Requires-Dist: importlib_metadata>=8.6.1; python_version < "3.10"
Requires-Dist: josepy>=2.0.0
Requires-Dist: parsedatetime>=2.6
Requires-Dist: pyrfc3339
Requires-Dist: pywin32>=300; sys_platform == "win32"
Provides-Extra: dev
Requires-Dist: azure-devops; extra == "dev"
Requires-Dist: build; extra == "dev"
Requires-Dist: ipdb; extra == "dev"
Requires-Dist: poetry-plugin-export>=1.9.0; extra == "dev"
Requires-Dist: poetry>=1.2.0; extra == "dev"
Requires-Dist: towncrier; extra == "dev"
Requires-Dist: twine; extra == "dev"
Provides-Extra: docs
Requires-Dist: Sphinx>=1.2; extra == "docs"
Requires-Dist: sphinx_rtd_theme; extra == "docs"
Provides-Extra: test
Requires-Dist: coverage; extra == "test"
Requires-Dist: mypy; extra == "test"
Requires-Dist: pip; extra == "test"
Requires-Dist: pylint; extra == "test"
Requires-Dist: pytest; extra == "test"
Requires-Dist: pytest-cov>=4.1.0; extra == "test"
Requires-Dist: pytest-xdist; extra == "test"
Requires-Dist: ruff; extra == "test"
Requires-Dist: setuptools; extra == "test"
Requires-Dist: tox; extra == "test"
Requires-Dist: types-httplib2; extra == "test"
Requires-Dist: types-pyRFC3339; extra == "test"
Requires-Dist: types-pywin32; extra == "test"
Requires-Dist: types-requests; extra == "test"
Requires-Dist: types-setuptools; extra == "test"
Requires-Dist: uv; extra == "test"
Requires-Dist: wheel; extra == "test"
Provides-Extra: all
Requires-Dist: certbot[dev,docs,test]; extra == "all"
Dynamic: license-file
Dynamic: requires-dist
